bmai_dm_hbase/__init__.py
bmai_dm_hbase/conf_reader.py
bmai_dm_hbase/hbase_client.py
bmai_dm_hbase/reconnection.py
bmai_dm_hbase-0.2.2.dist-info/LICENSE.md
bmai_dm_hbase-0.2.2.dist-info/METADATA
bmai_dm_hbase-0.2.2.dist-info/WHEEL
bmai_dm_hbase-0.2.2.dist-info/top_level.txt
bmai_dm_hbase-0.2.2.dist-info/RECORD
