Metadata-Version: 2.1
Name: bmai-dm-hbase
Version: 0.2.2
Summary: Data mining Group hbase utils
Home-page: http://gitlab.admin.bluemoon.com.cn/BigData-DataAlgorithm/dm-hbase.git
Author: Shuxin Liang
Author-email: liangshuxin1@bluemoon.com.cn
License: MIT License        
Platform: UNKNOWN
Requires-Python: >=3.6
License-File: LICENSE.md
Requires-Dist: ruamel.yaml (>=0.15.0)
Requires-Dist: thrift (>=0.15.0)
Requires-Dist: thrift-sasl (>=0.4.2)
Requires-Dist: thriftpy2 (>=0.4.14)
Requires-Dist: happybase (>=1.2.0)
Requires-Dist: pandas (>=1.3.4)
